Workbook

Sheet GABI
C7: Investimento | H7: Parâmetros | T7: Projeção
C10: (R$) Verba em Tráfego | D10: 100000 | H10: Meta de Leads | I10: Leads Org | J10: Leads Pago | K10: Leads Total | M10: Meta de Vendas | N10: Vendas | O10: Faturamento | P10: Roas | T10: Venda | V10: Custo por Lead
C11: (%) Verba Utilizada | D11: 0.2 | I11: =K15 -> 700 | J11: =1887 -> 1887 | K11: =I11+J11 -> 2587 | N11: =P18 -> 47.333333 | O11: =P18*P14 -> 568000 | P11: =IFERROR( O11/D10, "") -> 5.68 | V11: Cenário Ideal | Y11: Cenário Ótimo | AB11: Cenário Bom | AE11: Cenário Padrão | AH11: Cenário Ruim | AK11: Cenário Péssimo | AN11: Cenário Catastrófico
V12: =I27 -> 30 | Y12: =I26 -> 40 | AB12: =I25 -> 50 | AE12: =I24 -> 60 | AH12: =I23 -> 70 | AK12: =I22 -> 80 | AN12: =I21 -> 90
V13: =IF($U$33, FLOOR( K27, '⚙️Configurações'!$E$3), K27) -> 4033 | Y13: =IF($U$33, FLOOR( K26, '⚙️Configurações'!$E$3), K26) -> 3200 | AB13: =IF($U$33, FLOOR( K25, '⚙️Configurações'!$E$3), K25) -> 2700 | AE13: =IF($U$33, FLOOR( K24, '⚙️Configurações'!$E$3), K24) -> 2366 | AH13: =IF($U$33, FLOOR( K23, '⚙️Configurações'!$E$3), K23) -> 2128 | AK13: =IF($U$33, FLOOR( K22, '⚙️Configurações'!$E$3), K22) -> 1950 | AN13: =IF($U$33, FLOOR( K21, '⚙️Configurações'!$E$3), K21) -> 1811
C14: (%) Verba em Captação | D14: 1 | H14: Leads Orgânicos | I14: Social | J14: Mailing | K14: Média Org | M14: Ticket Médio | N14: Ticket | O14: % Taxas | P14: =N15 -P15 -> 12000 | T14: Conversão | U14: =N27 -> 0.08 | V14: =IF($U$33, FLOOR( ROUNDDOWN(V$13*$U14,0), '⚙️Configurações'!$C$3), ROUNDDOWN(V$13*$U14,0) ) -> 322 | W14: =IF($U$33, FLOOR( V14*$P$14, '⚙️Configurações'!$D$3), V14*$P$14) -> 3864000 | X14: =W14/$D$10 -> 38.64 | Y14: =IF($U$33, FLOOR( ROUNDDOWN(Y$13*$U14,0), '⚙️Configurações'!$C$3), ROUNDDOWN(Y$13*$U14,0) ) -> 256 | Z14: =IF($U$33, FLOOR( Y14*$P$14, '⚙️Configurações'!$D$3), Y14*$P$14) -> 3072000 | AA14: =Z14/$D$10 -> 30.72 | AB14: =IF($U$33, FLOOR( ROUNDDOWN(AB$13*$U14,0), '⚙️Configurações'!$C$3), ROUNDDOWN(AB$13*$U14,0) ) -> 216 | AC14: =IF($U$33, FLOOR( AB14*$P$14, '⚙️Configurações'!$D$3), AB14*$P$14) -> 2592000 | AD14: =AC14/$D$10 -> 25.92 | AE14: =IF($U$33, FLOOR( ROUNDDOWN(AE$13*$U14,0), '⚙️Configurações'!$C$3), ROUNDDOWN(AE$13*$U14,0) ) -> 189 | AF14: =IF($U$33, FLOOR( AE14*$P$14, '⚙️Configurações'!$D$3), AE14*$P$14) -> 2268000 | AG14: =AF14/$D$10 -> 22.68 | AH14: =IF($U$33, FLOOR( ROUNDDOWN(AH$13*$U14,0), '⚙️Configurações'!$C$3), ROUNDDOWN(AH$13*$U14,0) ) -> 170 | AI14: =IF($U$33, FLOOR( AH14*$P$14, '⚙️Configurações'!$D$3), AH14*$P$14) -> 2040000 | AJ14: =AI14/$D$10 -> 20.4 | AK14: =IF($U$33, FLOOR( ROUNDDOWN(AK$13*$U14,0), '⚙️Configurações'!$C$3), ROUNDDOWN(AK$13*$U14,0) ) -> 156 | AL14: =IF($U$33, FLOOR( AK14*$P$14, '⚙️Configurações'!$D$3), AK14*$P$14) -> 1872000 | AM14: =AL14/$D$10 -> 18.72 | AN14: =IF($U$33, FLOOR( ROUNDDOWN(AN$13*$U14,0), '⚙️Configurações'!$C$3), ROUNDDOWN(AN$13*$U14,0) ) -> 144 | AO14: =IF($U$33, FLOOR( AN14*$P$14, '⚙️Configurações'!$D$3), AN14*$P$14) -> 1728000 | AP14: =AO14/$D$10 -> 17.28
C15: (R$) Verba em Captação | D15: =D$10*D14 -> 100000 | I15: 200 | J15: 500 | K15: =sum(I15:J15) -> 700 | N15: 12000 | O15: 0 | P15: =N15*O15 -> 0
C16: (%) Verba em Lembrete | D16: 0 | U16: =N26 -> 0.06 | V16: =IF($U$33, FLOOR( ROUNDDOWN(V$13*$U16,0), '⚙️Configurações'!$C$3), ROUNDDOWN(V$13*$U16,0) ) -> 241 | W16: =IF($U$33, FLOOR( V16*$P$14, '⚙️Configurações'!$D$3), V16*$P$14) -> 2892000 | X16: =W16/$D$10 -> 28.92 | Y16: =IF($U$33, FLOOR( ROUNDDOWN(Y$13*$U16,0), '⚙️Configurações'!$C$3), ROUNDDOWN(Y$13*$U16,0) ) -> 192 | Z16: =IF($U$33, FLOOR( Y16*$P$14, '⚙️Configurações'!$D$3), Y16*$P$14) -> 2304000 | AA16: =Z16/$D$10 -> 23.04 | AB16: =IF($U$33, FLOOR( ROUNDDOWN(AB$13*$U16,0), '⚙️Configurações'!$C$3), ROUNDDOWN(AB$13*$U16,0) ) -> 162 | AC16: =IF($U$33, FLOOR( AB16*$P$14, '⚙️Configurações'!$D$3), AB16*$P$14) -> 1944000 | AD16: =AC16/$D$10 -> 19.44 | AE16: =IF($U$33, FLOOR( ROUNDDOWN(AE$13*$U16,0), '⚙️Configurações'!$C$3), ROUNDDOWN(AE$13*$U16,0) ) -> 141 | AF16: =IF($U$33, FLOOR( AE16*$P$14, '⚙️Configurações'!$D$3), AE16*$P$14) -> 1692000 | AG16: =AF16/$D$10 -> 16.92 | AH16: =IF($U$33, FLOOR( ROUNDDOWN(AH$13*$U16,0), '⚙️Configurações'!$C$3), ROUNDDOWN(AH$13*$U16,0) ) -> 127 | AI16: =IF($U$33, FLOOR( AH16*$P$14, '⚙️Configurações'!$D$3), AH16*$P$14) -> 1524000 | AJ16: =AI16/$D$10 -> 15.24 | AK16: =IF($U$33, FLOOR( ROUNDDOWN(AK$13*$U16,0), '⚙️Configurações'!$C$3), ROUNDDOWN(AK$13*$U16,0) ) -> 117 | AL16: =IF($U$33, FLOOR( AK16*$P$14, '⚙️Configurações'!$D$3), AK16*$P$14) -> 1404000 | AM16: =AL16/$D$10 -> 14.04 | AN16: =IF($U$33, FLOOR( ROUNDDOWN(AN$13*$U16,0), '⚙️Configurações'!$C$3), ROUNDDOWN(AN$13*$U16,0) ) -> 108 | AO16: =IF($U$33, FLOOR( AN16*$P$14, '⚙️Configurações'!$D$3), AN16*$P$14) -> 1296000 | AP16: =AO16/$D$10 -> 12.96
C17: (R$) Verba em Lembrete | D17: =D$10*D16 -> 0 | H17: CPL | I17: CPL Méd | J17: (%) Variação | K17: Média Pago | M17: Vendas | N17: (%) Conversão | O17: (%) Variação | P17: Média Vendas
C18: (%) Verba em Aquecimento | D18: 0 | I18: 60 | J18: 10 | K18: =D15/I18 -> 1666.6667 | N18: 0.02 | O18: 0.02 | P18: =(K18+K15)*N18 -> 47.333333 | U18: =N25 -> 0.04 | V18: =IF($U$33, FLOOR( ROUNDDOWN(V$13*$U18,0), '⚙️Configurações'!$C$3), ROUNDDOWN(V$13*$U18,0) ) -> 161 | W18: =IF($U$33, FLOOR( V18*$P$14, '⚙️Configurações'!$D$3), V18*$P$14) -> 1932000 | X18: =W18/$D$10 -> 19.32 | Y18: =IF($U$33, FLOOR( ROUNDDOWN(Y$13*$U18,0), '⚙️Configurações'!$C$3), ROUNDDOWN(Y$13*$U18,0) ) -> 128 | Z18: =IF($U$33, FLOOR( Y18*$P$14, '⚙️Configurações'!$D$3), Y18*$P$14) -> 1536000 | AA18: =Z18/$D$10 -> 15.36 | AB18: =IF($U$33, FLOOR( ROUNDDOWN(AB$13*$U18,0), '⚙️Configurações'!$C$3), ROUNDDOWN(AB$13*$U18,0) ) -> 108 | AC18: =IF($U$33, FLOOR( AB18*$P$14, '⚙️Configurações'!$D$3), AB18*$P$14) -> 1296000 | AD18: =AC18/$D$10 -> 12.96 | AE18: =IF($U$33, FLOOR( ROUNDDOWN(AE$13*$U18,0), '⚙️Configurações'!$C$3), ROUNDDOWN(AE$13*$U18,0) ) -> 94 | AF18: =IF($U$33, FLOOR( AE18*$P$14, '⚙️Configurações'!$D$3), AE18*$P$14) -> 1128000 | AG18: =AF18/$D$10 -> 11.28 | AH18: =IF($U$33, FLOOR( ROUNDDOWN(AH$13*$U18,0), '⚙️Configurações'!$C$3), ROUNDDOWN(AH$13*$U18,0) ) -> 85 | AI18: =IF($U$33, FLOOR( AH18*$P$14, '⚙️Configurações'!$D$3), AH18*$P$14) -> 1020000 | AJ18: =AI18/$D$10 -> 10.2 | AK18: =IF($U$33, FLOOR( ROUNDDOWN(AK$13*$U18,0), '⚙️Configurações'!$C$3), ROUNDDOWN(AK$13*$U18,0) ) -> 78 | AL18: =IF($U$33, FLOOR( AK18*$P$14, '⚙️Configurações'!$D$3), AK18*$P$14) -> 936000 | AM18: =AL18/$D$10 -> 9.36 | AN18: =IF($U$33, FLOOR( ROUNDDOWN(AN$13*$U18,0), '⚙️Configurações'!$C$3), ROUNDDOWN(AN$13*$U18,0) ) -> 72 | AO18: =IF($U$33, FLOOR( AN18*$P$14, '⚙️Configurações'!$D$3), AN18*$P$14) -> 864000 | AP18: =AO18/$D$10 -> 8.64
C19: (R$) Verba em Aquecimento | D19: =D$10*D18 -> 0
C20: (%) Verba em Evento | D20: 0 | H20: Leads Pagos | I20: CPL | J20: Leads Pagos | K20: Total Geral | M20: Conversão | N20: Conversão | O20: Vendas | P20: Faturamento | U20: =N24 -> 0.02 | V20: =IF($U$33, FLOOR( ROUNDDOWN(V$13*$U20,0), '⚙️Configurações'!$C$3), ROUNDDOWN(V$13*$U20,0) ) -> 80 | W20: =IF($U$33, FLOOR( V20*$P$14, '⚙️Configurações'!$D$3), V20*$P$14) -> 960000 | X20: =W20/$D$10 -> 9.6 | Y20: =IF($U$33, FLOOR( ROUNDDOWN(Y$13*$U20,0), '⚙️Configurações'!$C$3), ROUNDDOWN(Y$13*$U20,0) ) -> 64 | Z20: =IF($U$33, FLOOR( Y20*$P$14, '⚙️Configurações'!$D$3), Y20*$P$14) -> 768000 | AA20: =Z20/$D$10 -> 7.68 | AB20: =IF($U$33, FLOOR( ROUNDDOWN(AB$13*$U20,0), '⚙️Configurações'!$C$3), ROUNDDOWN(AB$13*$U20,0) ) -> 54 | AC20: =IF($U$33, FLOOR( AB20*$P$14, '⚙️Configurações'!$D$3), AB20*$P$14) -> 648000 | AD20: =AC20/$D$10 -> 6.48 | AE20: =IF($U$33, FLOOR( ROUNDDOWN(AE$13*$U20,0), '⚙️Configurações'!$C$3), ROUNDDOWN(AE$13*$U20,0) ) -> 47 | AF20: =IF($U$33, FLOOR( AE20*$P$14, '⚙️Configurações'!$D$3), AE20*$P$14) -> 564000 | AG20: =AF20/$D$10 -> 5.64 | AH20: =IF($U$33, FLOOR( ROUNDDOWN(AH$13*$U20,0), '⚙️Configurações'!$C$3), ROUNDDOWN(AH$13*$U20,0) ) -> 42 | AI20: =IF($U$33, FLOOR( AH20*$P$14, '⚙️Configurações'!$D$3), AH20*$P$14) -> 504000 | AJ20: =AI20/$D$10 -> 5.04 | AK20: =IF($U$33, FLOOR( ROUNDDOWN(AK$13*$U20,0), '⚙️Configurações'!$C$3), ROUNDDOWN(AK$13*$U20,0) ) -> 39 | AL20: =IF($U$33, FLOOR( AK20*$P$14, '⚙️Configurações'!$D$3), AK20*$P$14) -> 468000 | AM20: =AL20/$D$10 -> 4.68 | AN20: =IF($U$33, FLOOR( ROUNDDOWN(AN$13*$U20,0), '⚙️Configurações'!$C$3), ROUNDDOWN(AN$13*$U20,0) ) -> 36 | AO20: =IF($U$33, FLOOR( AN20*$P$14, '⚙️Configurações'!$D$3), AN20*$P$14) -> 432000 | AP20: =AO20/$D$10 -> 4.32
C21: (R$) Verba em Evento | D21: =D$10*D20 -> 0 | H21: Cenário Catastrófico | I21: =I$18 + 3*J$18 -> 90 | J21: =ROUNDDOWN(D$15/I21,0) -> 1111 | K21: =J21+$K$15 -> 1811 | M21: Cenário Catastrófico | N21: =N$18 -3*O$18 -> -0.04 | O21: =$K$24*N21 -> -94.64 | P21: =O21*$P$14 -> -1135680
C22: (%) Verba em Venda | D22: 0 | H22: Cenário Péssimo | I22: =I$18 + 2*J$18 -> 80 | J22: =ROUNDDOWN(D$15/I22,0) -> 1250 | K22: =J22+$K$15 -> 1950 | M22: Cenário Péssimo | N22: =N$18 -2*O$18 -> -0.02 | O22: =$K$24*N22 -> -47.32 | P22: =O22*$P$14 -> -567840 | U22: =N23 -> 0 | V22: =IF($U$33, FLOOR( ROUNDDOWN(V$13*$U22,0), '⚙️Configurações'!$C$3), ROUNDDOWN(V$13*$U22,0) ) -> 0 | W22: =IF($U$33, FLOOR( V22*$P$14, '⚙️Configurações'!$D$3), V22*$P$14) -> 0 | X22: =W22/$D$10 -> 0 | Y22: =IF($U$33, FLOOR( ROUNDDOWN(Y$13*$U22,0), '⚙️Configurações'!$C$3), ROUNDDOWN(Y$13*$U22,0) ) -> 0 | Z22: =IF($U$33, FLOOR( Y22*$P$14, '⚙️Configurações'!$D$3), Y22*$P$14) -> 0 | AA22: =Z22/$D$10 -> 0 | AB22: =IF($U$33, FLOOR( ROUNDDOWN(AB$13*$U22,0), '⚙️Configurações'!$C$3), ROUNDDOWN(AB$13*$U22,0) ) -> 0 | AC22: =IF($U$33, FLOOR( AB22*$P$14, '⚙️Configurações'!$D$3), AB22*$P$14) -> 0 | AD22: =AC22/$D$10 -> 0 | AE22: =IF($U$33, FLOOR( ROUNDDOWN(AE$13*$U22,0), '⚙️Configurações'!$C$3), ROUNDDOWN(AE$13*$U22,0) ) -> 0 | AF22: =IF($U$33, FLOOR( AE22*$P$14, '⚙️Configurações'!$D$3), AE22*$P$14) -> 0 | AG22: =AF22/$D$10 -> 0 | AH22: =IF($U$33, FLOOR( ROUNDDOWN(AH$13*$U22,0), '⚙️Configurações'!$C$3), ROUNDDOWN(AH$13*$U22,0) ) -> 0 | AI22: =IF($U$33, FLOOR( AH22*$P$14, '⚙️Configurações'!$D$3), AH22*$P$14) -> 0 | AJ22: =AI22/$D$10 -> 0 | AK22: =IF($U$33, FLOOR( ROUNDDOWN(AK$13*$U22,0), '⚙️Configurações'!$C$3), ROUNDDOWN(AK$13*$U22,0) ) -> 0 | AL22: =IF($U$33, FLOOR( AK22*$P$14, '⚙️Configurações'!$D$3), AK22*$P$14) -> 0 | AM22: =AL22/$D$10 -> 0 | AN22: =IF($U$33, FLOOR( ROUNDDOWN(AN$13*$U22,0), '⚙️Configurações'!$C$3), ROUNDDOWN(AN$13*$U22,0) ) -> 0 | AO22: =IF($U$33, FLOOR( AN22*$P$14, '⚙️Configurações'!$D$3), AN22*$P$14) -> 0 | AP22: =AO22/$D$10 -> 0
C23: (R$) Verba em Venda | D23: =D$10*D22 -> 0 | H23: Cenário Ruim | I23: =I$18 + 1*J$18 -> 70 | J23: =ROUNDDOWN(D$15/I23,0) -> 1428 | K23: =J23+$K$15 -> 2128 | M23: Cenário Ruim | N23: =N$18 - 1*O$18 -> 0 | O23: =$K$24*N23 -> 0 | P23: =O23*$P$14 -> 0
C24: (%) Verba em Espera | D24: 0 | H24: Cenário Padrão | I24: =I$18 -> 60 | J24: =ROUNDDOWN(D$15/I24,0) -> 1666 | K24: =J24+$K$15 -> 2366 | M24: Cenário Padrão | N24: =N$18 -> 0.02 | O24: =$K$24*N24 -> 47.32 | P24: =O24*$P$14 -> 567840 | U24: =N22 -> -0.02 | V24: =IF($U$33, FLOOR( ROUNDDOWN(V$13*$U24,0), '⚙️Configurações'!$C$3), ROUNDDOWN(V$13*$U24,0) ) -> -80 | W24: =IF($U$33, FLOOR( V24*$P$14, '⚙️Configurações'!$D$3), V24*$P$14) -> -960000 | X24: =W24/$D$10 -> -9.6 | Y24: =IF($U$33, FLOOR( ROUNDDOWN(Y$13*$U24,0), '⚙️Configurações'!$C$3), ROUNDDOWN(Y$13*$U24,0) ) -> -64 | Z24: =IF($U$33, FLOOR( Y24*$P$14, '⚙️Configurações'!$D$3), Y24*$P$14) -> -768000 | AA24: =Z24/$D$10 -> -7.68 | AB24: =IF($U$33, FLOOR( ROUNDDOWN(AB$13*$U24,0), '⚙️Configurações'!$C$3), ROUNDDOWN(AB$13*$U24,0) ) -> -54 | AC24: =IF($U$33, FLOOR( AB24*$P$14, '⚙️Configurações'!$D$3), AB24*$P$14) -> -648000 | AD24: =AC24/$D$10 -> -6.48 | AE24: =IF($U$33, FLOOR( ROUNDDOWN(AE$13*$U24,0), '⚙️Configurações'!$C$3), ROUNDDOWN(AE$13*$U24,0) ) -> -47 | AF24: =IF($U$33, FLOOR( AE24*$P$14, '⚙️Configurações'!$D$3), AE24*$P$14) -> -564000 | AG24: =AF24/$D$10 -> -5.64 | AH24: =IF($U$33, FLOOR( ROUNDDOWN(AH$13*$U24,0), '⚙️Configurações'!$C$3), ROUNDDOWN(AH$13*$U24,0) ) -> -42 | AI24: =IF($U$33, FLOOR( AH24*$P$14, '⚙️Configurações'!$D$3), AH24*$P$14) -> -504000 | AJ24: =AI24/$D$10 -> -5.04 | AK24: =IF($U$33, FLOOR( ROUNDDOWN(AK$13*$U24,0), '⚙️Configurações'!$C$3), ROUNDDOWN(AK$13*$U24,0) ) -> -39 | AL24: =IF($U$33, FLOOR( AK24*$P$14, '⚙️Configurações'!$D$3), AK24*$P$14) -> -468000 | AM24: =AL24/$D$10 -> -4.68 | AN24: =IF($U$33, FLOOR( ROUNDDOWN(AN$13*$U24,0), '⚙️Configurações'!$C$3), ROUNDDOWN(AN$13*$U24,0) ) -> -36 | AO24: =IF($U$33, FLOOR( AN24*$P$14, '⚙️Configurações'!$D$3), AN24*$P$14) -> -432000 | AP24: =AO24/$D$10 -> -4.32
C25: (R$) Verba em Venda | D25: =D$10*D24 -> 0 | H25: Cenário Bom | I25: =I$18 - 1*J$18 -> 50 | J25: =ROUNDDOWN(D$15/I25,0) -> 2000 | K25: =J25+$K$15 -> 2700 | M25: Cenário Bom | N25: =N$18 + 1*O$18 -> 0.04 | O25: =$K$24*N25 -> 94.64 | P25: =O25*$P$14 -> 1135680
C26: (%) Verba em Tiro de Alerta | D26: 0 | H26: Cenário Ótimo | I26: =I$18 - 2*J$18 -> 40 | J26: =ROUNDDOWN(D$15/I26,0) -> 2500 | K26: =J26+$K$15 -> 3200 | M26: Cenário Ótimo | N26: =N$18 + 2*O$18 -> 0.06 | O26: =$K$24*N26 -> 141.96 | P26: =O26*$P$14 -> 1703520 | U26: =N21 -> -0.04 | V26: =IF($U$33, FLOOR( ROUNDDOWN(V$13*$U26,0), '⚙️Configurações'!$C$3), ROUNDDOWN(V$13*$U26,0) ) -> -161 | W26: =IF($U$33, FLOOR( V26*$P$14, '⚙️Configurações'!$D$3), V26*$P$14) -> -1932000 | X26: =W26/$D$10 -> -19.32 | Y26: =IF($U$33, FLOOR( ROUNDDOWN(Y$13*$U26,0), '⚙️Configurações'!$C$3), ROUNDDOWN(Y$13*$U26,0) ) -> -128 | Z26: =IF($U$33, FLOOR( Y26*$P$14, '⚙️Configurações'!$D$3), Y26*$P$14) -> -1536000 | AA26: =Z26/$D$10 -> -15.36 | AB26: =IF($U$33, FLOOR( ROUNDDOWN(AB$13*$U26,0), '⚙️Configurações'!$C$3), ROUNDDOWN(AB$13*$U26,0) ) -> -108 | AC26: =IF($U$33, FLOOR( AB26*$P$14, '⚙️Configurações'!$D$3), AB26*$P$14) -> -1296000 | AD26: =AC26/$D$10 -> -12.96 | AE26: =IF($U$33, FLOOR( ROUNDDOWN(AE$13*$U26,0), '⚙️Configurações'!$C$3), ROUNDDOWN(AE$13*$U26,0) ) -> -94 | AF26: =IF($U$33, FLOOR( AE26*$P$14, '⚙️Configurações'!$D$3), AE26*$P$14) -> -1128000 | AG26: =AF26/$D$10 -> -11.28 | AH26: =IF($U$33, FLOOR( ROUNDDOWN(AH$13*$U26,0), '⚙️Configurações'!$C$3), ROUNDDOWN(AH$13*$U26,0) ) -> -85 | AI26: =IF($U$33, FLOOR( AH26*$P$14, '⚙️Configurações'!$D$3), AH26*$P$14) -> -1020000 | AJ26: =AI26/$D$10 -> -10.2 | AK26: =IF($U$33, FLOOR( ROUNDDOWN(AK$13*$U26,0), '⚙️Configurações'!$C$3), ROUNDDOWN(AK$13*$U26,0) ) -> -78 | AL26: =IF($U$33, FLOOR( AK26*$P$14, '⚙️Configurações'!$D$3), AK26*$P$14) -> -936000 | AM26: =AL26/$D$10 -> -9.36 | AN26: =IF($U$33, FLOOR( ROUNDDOWN(AN$13*$U26,0), '⚙️Configurações'!$C$3), ROUNDDOWN(AN$13*$U26,0) ) -> -72 | AO26: =IF($U$33, FLOOR( AN26*$P$14, '⚙️Configurações'!$D$3), AN26*$P$14) -> -864000 | AP26: =AO26/$D$10 -> -8.64
C27: (R$) Verba em Reabertua | D27: =D$10*D26 -> 0 | H27: Cenário A-HA | I27: =I$18 - 3*J$18 -> 30 | J27: =ROUNDDOWN(D$15/I27,0) -> 3333 | K27: =J27+$K$15 -> 4033 | M27: Cenário Ideal | N27: =N$18 + 3*O$18 -> 0.08 | O27: =$K$24*N27 -> 189.28 | P27: =O27*$P$14 -> 2271360
S33: Arrendondar? | U33: FALSE

Sheet ⚙️Configurações
B2: Arredondamento | C2: Quantidade Vendas | D2: Fatuamento Vendas | E2: Leads
C3: 10 | D3: 50000 | E3: 500
